pywe_message_reply/__init__.py
pywe_message_reply/pymsgreply.py
pywe_message_reply-1.0.2.dist-info/DESCRIPTION.rst
pywe_message_reply-1.0.2.dist-info/METADATA
pywe_message_reply-1.0.2.dist-info/RECORD
pywe_message_reply-1.0.2.dist-info/WHEEL
pywe_message_reply-1.0.2.dist-info/metadata.json
pywe_message_reply-1.0.2.dist-info/top_level.txt
